CHANGES.txt
LICENSE.txt
MANIFEST.in
README.txt
setup.py
js/__init__.py
js.jquery_jqote2.egg-info/PKG-INFO
js.jquery_jqote2.egg-info/SOURCES.txt
js.jquery_jqote2.egg-info/dependency_links.txt
js.jquery_jqote2.egg-info/entry_points.txt
js.jquery_jqote2.egg-info/namespace_packages.txt
js.jquery_jqote2.egg-info/not-zip-safe
js.jquery_jqote2.egg-info/requires.txt
js.jquery_jqote2.egg-info/top_level.txt
js/jquery_jqote2/__init__.py
js/jquery_jqote2/test_jquery.jqote2.txt
js/jquery_jqote2/resources/README.txt
js/jquery_jqote2/resources/jquery.jqote2.js
js/jquery_jqote2/resources/jquery.jqote2.min.js