Metadata-Version: 1.0
Name: js.jquery-jqote2
Version: 0.9.7
Summary: Fanstatic packaging of jquery.jqote2
Home-page: UNKNOWN
Author: Stephane Klein
Author-email: stephane@harobed.org
License: BSD
Platform: UNKNOWN
